{"type": "FeatureCollection", "features": [{"type": "Feature", "id": 358763678, "geometry": {"type": "Point", "coordinates": [-123.934202, 40.189031]}, "properties": {"ele": "842", "gnis:feature_id": "221169", "name": "Clarks Butte", "natural": "peak"}}, {"type": "Feature", "id": 358763678, "geometry": {"type": "Point", "coordinates": [-123.934202, 40.189031]}, "properties": {"ele": "842", "gnis:feature_id": "221169", "name": "Clarks Butte", "natural": "peak"}}]}